odoo/addons/hr_timesheet_sheet_attendance/README.rst
odoo/addons/hr_timesheet_sheet_attendance/__init__.py
odoo/addons/hr_timesheet_sheet_attendance/__manifest__.py
odoo/addons/hr_timesheet_sheet_attendance/i18n/es.po
odoo/addons/hr_timesheet_sheet_attendance/i18n/hr_timesheet_sheet_attendance.pot
odoo/addons/hr_timesheet_sheet_attendance/i18n/it.po
odoo/addons/hr_timesheet_sheet_attendance/i18n/pt_BR.po
odoo/addons/hr_timesheet_sheet_attendance/models/__init__.py
odoo/addons/hr_timesheet_sheet_attendance/models/hr_attendance.py
odoo/addons/hr_timesheet_sheet_attendance/models/hr_timesheet_sheet.py
odoo/addons/hr_timesheet_sheet_attendance/readme/CONTRIBUTORS.md
odoo/addons/hr_timesheet_sheet_attendance/readme/DESCRIPTION.md
odoo/addons/hr_timesheet_sheet_attendance/readme/INSTALL.md
odoo/addons/hr_timesheet_sheet_attendance/readme/ROADMAP.md
odoo/addons/hr_timesheet_sheet_attendance/readme/USAGE.md
odoo/addons/hr_timesheet_sheet_attendance/static/description/icon.png
odoo/addons/hr_timesheet_sheet_attendance/static/description/index.html
odoo/addons/hr_timesheet_sheet_attendance/tests/__init__.py
odoo/addons/hr_timesheet_sheet_attendance/tests/hr_timesheet_sheet_test_cases.py
odoo/addons/hr_timesheet_sheet_attendance/tests/test_hr_attendance.py
odoo/addons/hr_timesheet_sheet_attendance/tests/test_hr_timesheet_sheet.py
odoo/addons/hr_timesheet_sheet_attendance/views/hr_attendance_view.xml
odoo/addons/hr_timesheet_sheet_attendance/views/hr_timesheet_sheet_view.xml
odoo_addon_hr_timesheet_sheet_attendance-18.0.1.0.1.dist-info/METADATA
odoo_addon_hr_timesheet_sheet_attendance-18.0.1.0.1.dist-info/WHEEL
odoo_addon_hr_timesheet_sheet_attendance-18.0.1.0.1.dist-info/top_level.txt
odoo_addon_hr_timesheet_sheet_attendance-18.0.1.0.1.dist-info/RECORD
